{
  "config.title": "MemoBox",
  "config.paths.title": "基本パス",
  "config.assets.title": "テンプレートとメタデータ",
  "config.creation.title": "メモ作成とクイックメモ",
  "config.browse.title": "一覧表示とオープン",
  "config.search.title": "検索と関連メモ",
  "config.admin.title": "管理画面と言語設定",
  "config.ai.title": "AI",
  "commands.newMemo.title": "MemoBox: 新規メモ",
  "commands.quickMemo.title": "MemoBox: 今日のクイックメモ",
  "commands.listMemos.title": "MemoBox: 一覧 / 編集",
  "commands.listTags.title": "MemoBox: タグから開く",
  "commands.createWorkspace.title": "MemoBox: ワークスペースを作成",
  "commands.grepMemos.title": "MemoBox: 検索",
  "commands.todoMemos.title": "MemoBox: Todo",
  "commands.relatedMemos.title": "MemoBox: 関連メモ",
  "commands.redateMemo.title": "MemoBox: 日付を今日に変更",
  "commands.refreshIndex.title": "MemoBox: インデックスを更新",
  "commands.rebuildIndex.title": "MemoBox: インデックスを再構築",
  "commands.clearIndexCache.title": "MemoBox: インデックスキャッシュを削除",
  "commands.openMemoFolder.title": "MemoBox: メモフォルダを開く",
  "commands.openMarkdownInBrowser.title": "MemoBox: Markdown をブラウザで開く",
  "commands.openSettings.title": "MemoBox: 設定を開く",
  "commands.openSetup.title": "MemoBox: 初期設定を開く",
  "commands.openAdmin.title": "MemoBox: 管理画面",
  "commands.aiAutoTag.title": "MemoBox: AI タグ提案",
  "commands.aiSummarize.title": "MemoBox: AI 要約",
  "commands.aiGenerateTitle.title": "MemoBox: AI タイトル生成",
  "commands.aiProofread.title": "MemoBox: AI 校正",
  "commands.aiTranslate.title": "MemoBox: AI 翻訳",
  "commands.aiQuestion.title": "MemoBox: AI 質問",
  "commands.aiSuggestTemplate.title": "MemoBox: AI テンプレート提案",
  "commands.aiReport.title": "MemoBox: AI レポート",
  "commands.aiLinkSuggest.title": "MemoBox: AI リンク提案",
  "commands.aiSetApiKey.title": "MemoBox: AI API キーを保存",
  "commands.aiClearApiKey.title": "MemoBox: 保存済み AI API キーを削除",
  "settings.memodir.description": "メモファイルを保存するディレクトリの絶対パスです。",
  "settings.datePathFormat.description": "メモ作成時に使う日付ベースのサブフォルダ形式です。例: `yyyy/MM` や `yyyy/MM/dd`。",
  "settings.memotemplate.description": "新規メモ作成時に使う任意のテンプレートファイルです。",
  "settings.metaDir.description": "`memobox.memodir` 配下でテンプレート、スニペット、インデックスを保存するメタデータ用ディレクトリです。",
  "settings.templatesDir.description": "テンプレートディレクトリの絶対パスを任意で指定します。空の場合は `<memodir>/<metaDir>/templates` を使います。",
  "settings.snippetsDir.description": "スニペットディレクトリの絶対パスを任意で指定します。空の場合は `<memodir>/<metaDir>/snippets` を使います。",
  "settings.searchMaxResults.description": "Grep と Todo が返す一致件数の上限です。上限を超えると結果は打ち切られます。",
  "settings.excludeDirectories.description": "メモルートを再帰走査するときに除外するディレクトリ名です。大文字小文字を区別せず、どの階層でも一致します。",
  "settings.maxScanDepth.description": "`memobox.memodir` 配下で走査する最大ディレクトリ深度です。`0` はメモルート直下のファイルのみ、`1` は1階層下まで、以降も同様です。",
  "settings.relatedMemoLimit.description": "`MemoBox: Related Memos` で表示する関連メモ数の上限です。",
  "settings.titlePrefix.description": "クイックメモの各追記見出しの先頭に挿入する文字列です。",
  "settings.dateFormat.description": "クイックメモ見出しで使う date-fns 形式です。",
  "settings.memoNewFilenameFromClipboard.description": "選択文字がない場合に、クリップボード内容を新規メモ名の候補に使います。",
  "settings.memoNewFilenameFromSelection.description": "アクティブエディタの選択文字列を新規メモ名の候補に使います。",
  "settings.memoNewFilenameDateSuffix.description": "新規メモの `yyyy-MM-dd` の後ろに付ける任意の date-fns 接尾辞です。",
  "settings.listSortOrder.description": "`MemoBox: List/Edit` の並び順です。どの選択肢でも新しいものが先頭になります。",
  "settings.listDisplayExtname.description": "`MemoBox: List/Edit` に表示する拡張子です。ドットは不要です。例: `[\"md\", \"txt\"]`。",
  "settings.displayFileBirthTime.description": "`MemoBox: List/Edit` で作成日時と更新日時の両方を表示します。",
  "settings.openMarkdownPreview.description": "New Memo、List/Edit、Re:Date、Admin などからメモを開くときに、組み込み Markdown Preview を横に開きます。",
  "settings.grepViewMode.description": "grep 結果の表示方法です。`quickPick` は対話型、`outputChannel` は軽量な出力ペイン、`both` は両方、document 系は Markdown 結果を文書として開きます。",
  "settings.todoPattern.description": "Todo 行を判定する正規表現です。既定値は `@todo:` を含む行に一致します。",
  "settings.recentCount.description": "Admin の Recent Files に表示する件数です。",
  "settings.adminOpenOnStartup.description": "VS Code 起動時に MemoBox Admin を自動で開きます。",
  "settings.locale.description": "MemoBox の UI 言語です。`auto` は VS Code の表示言語に従います。",
  "settings.aiEnabled.description": "MemoBox の AI 機能を有効にします。無効時は AI コマンドをメニューとコマンドパレットに表示しません。",
  "settings.ai.description": "AI の構造化設定です。provider ごとの接続情報は profile にまとめ、秘密情報は設定 JSON 直書きより VS Code SecretStorage または `apiKeyEnv` を推奨します。"
}
